uvkernel/__init__.py
uvkernel/ipynb_metadata.py
uvkernel/launcher.py
uvkernel-0.2.0.data/data/share/jupyter/kernels/uvkernel/kernel.json
uvkernel-0.2.0.data/data/share/jupyter/kernels/uvkernel/logo-32x32.png
uvkernel-0.2.0.data/data/share/jupyter/kernels/uvkernel/logo-64x64.png
uvkernel-0.2.0.data/data/share/jupyter/kernels/uvkernel/logo-svg.svg
uvkernel-0.2.0.dist-info/METADATA
uvkernel-0.2.0.dist-info/WHEEL
uvkernel-0.2.0.dist-info/licenses/LICENSE
uvkernel-0.2.0.dist-info/RECORD
