Metadata-Version: 2.4
Name: uvkernel
Version: 0.2.0
Summary: A jupyter kernel with automatic PEP723 environments, using uv
Author-email: Tobin Jones <tobin@davisjones.nz>
License-Expression: MIT
License-File: LICENSE
Requires-Python: >=3.11
Requires-Dist: nbformat>=5.10.4
Requires-Dist: uv>=0.7.19
